flask_stub_server/__init__.py
flask_stub_server/endpoint_gen/__init__.py
flask_stub_server/endpoint_gen/endpoint.py
flask_stub_server/endpoint_gen/endpoint_config.py
flask_stub_server/endpoint_gen/utils.py
src/__init__.py
src/endpoint_gen/__init__.py
src/endpoint_gen/endpoint.py
src/endpoint_gen/endpoint_config.py
src/endpoint_gen/utils.py
flask_stub_server-0.1.5a1.dist-info/LICENSE
flask_stub_server-0.1.5a1.dist-info/METADATA
flask_stub_server-0.1.5a1.dist-info/WHEEL
flask_stub_server-0.1.5a1.dist-info/top_level.txt
flask_stub_server-0.1.5a1.dist-info/RECORD
