Metadata-Version: 2.1
Name: flask-stub-server
Version: 0.1.5a1
Summary: This package provides the user with an easy to use endpoint generator, which that exposes endpoints that are defined through a config JSON file. Additionally, data files can be added and linked to return richer data.
Home-page: https://github.com/starlord-daniel/flask-stub-server
Author: Daniel Heinze
Author-email: daniel.heinze@microsoft.com
License: MIT
Keywords: python stub server flask
Platform: UNKNOWN
Classifier: Programming Language :: Python :: 3.9
Classifier: License :: OSI Approved :: MIT License
Classifier: Operating System :: OS Independent
Requires-Python: >=3.9
Requires-Dist: Flask (>=1.1.2)
